dmcutils/__init__.py
dmcutils/avi2hdf5.py
dmcutils/fitsreadermulti.py
dmcutils/neospool.py
dmcutils/whichandorfile.py
dmcutils-0.9.3.dist-info/METADATA
dmcutils-0.9.3.dist-info/RECORD
dmcutils-0.9.3.dist-info/WHEEL
dmcutils-0.9.3.dist-info/top_level.txt
