Metadata-Version: 2.1
Name: dmcutils
Version: 0.9.3
Summary: Utilities to read and plot DMC Experiment data
Home-page: https://github.com/scivision/dmcutils
Author: Michael Hirsch, Ph.D.
License: UNKNOWN
Platform: UNKNOWN
Classifier: Intended Audience :: Science/Research
Classifier: Development Status :: 3 - Alpha
Classifier: License :: OSI Approved :: MIT License
Classifier: Topic :: Scientific/Engineering :: Atmospheric Science
Classifier: Programming Language :: Python :: 3.6
Requires-Python: >=3.6
Provides-Extra: io
Provides-Extra: plot
Provides-Extra: web
Provides-Extra: tests
Requires-Dist: python-dateutil
Requires-Dist: pytz
Requires-Dist: pandas
Requires-Dist: h5py
Requires-Dist: scikit-image
Requires-Dist: imageio
Requires-Dist: histutils
Requires-Dist: morecvutils
Provides-Extra: io
Requires-Dist: astrometry-azel; extra == 'io'
Provides-Extra: plot
Requires-Dist: matplotlib; extra == 'plot'
Provides-Extra: tests
Requires-Dist: pytest; extra == 'tests'
Requires-Dist: coveralls; extra == 'tests'
Requires-Dist: flake8; extra == 'tests'
Requires-Dist: mypy; extra == 'tests'
Provides-Extra: web
Requires-Dist: flask; extra == 'web'
Requires-Dist: flask-limiter; extra == 'web'
